paginateit/__init__.py
paginateit/paginateit.py
paginateit-1.1.1.dist-info/AUTHORS.md
paginateit-1.1.1.dist-info/LICENSE
paginateit-1.1.1.dist-info/METADATA
paginateit-1.1.1.dist-info/WHEEL
paginateit-1.1.1.dist-info/top_level.txt
paginateit-1.1.1.dist-info/RECORD
