Metadata-Version: 2.1
Name: paginateit
Version: 1.1.1
Summary: Used to paginate REST API Calls / Mostly on MultiThreaded API Calls via Python
Home-page: https://github.com/manjesh23/paginateit
Author: Manjesh N
Author-email: manjesh_n@hotmail.com
License: UNKNOWN
Project-URL: Bug Reports, https://github.com/manjesh23/paginateit/issues
Project-URL: Source, https://github.com/manjesh23/paginateit
Keywords: API,REST,pagination,offset,skip,limit,recursion
Platform: UNKNOWN
Classifier: Development Status :: 5 - Production/Stable
Classifier: Intended Audience :: Developers
Classifier: Intended Audience :: End Users/Desktop
Classifier: Intended Audience :: Information Technology
Classifier: Intended Audience :: Customer Service
Classifier: License :: OSI Approved :: Apache Software License
Classifier: Natural Language :: English
Classifier: Programming Language :: Python :: 3.6
Classifier: Programming Language :: Python :: 3.7
Classifier: Programming Language :: Python :: 3.8
Classifier: Programming Language :: Python :: 3.9
Requires-Python: >=3.6
Provides-Extra: dev
Provides-Extra: test
